squidpy/__init__.py
squidpy/_compat.py
squidpy/_docs.py
squidpy/_utils.py
squidpy/_constants/__init__.py
squidpy/_constants/_constants.py
squidpy/_constants/_pkg_constants.py
squidpy/_constants/_utils.py
squidpy/datasets/_10x_datasets.py
squidpy/datasets/__init__.py
squidpy/datasets/_dataset.py
squidpy/datasets/_image.py
squidpy/datasets/_utils.py
squidpy/experimental/__init__.py
squidpy/experimental/im/__init__.py
squidpy/experimental/im/_detect_tissue.py
squidpy/experimental/im/_make_tiles.py
squidpy/experimental/im/_utils.py
squidpy/experimental/pl/__init__.py
squidpy/gr/__init__.py
squidpy/gr/_build.py
squidpy/gr/_ligrec.py
squidpy/gr/_nhood.py
squidpy/gr/_niche.py
squidpy/gr/_ppatterns.py
squidpy/gr/_ripley.py
squidpy/gr/_sepal.py
squidpy/gr/_utils.py
squidpy/im/__init__.py
squidpy/im/_container.py
squidpy/im/_coords.py
squidpy/im/_feature.py
squidpy/im/_feature_mixin.py
squidpy/im/_io.py
squidpy/im/_process.py
squidpy/im/_segment.py
squidpy/pl/__init__.py
squidpy/pl/_color_utils.py
squidpy/pl/_graph.py
squidpy/pl/_ligrec.py
squidpy/pl/_spatial.py
squidpy/pl/_spatial_utils.py
squidpy/pl/_utils.py
squidpy/pl/_var_by_distance.py
squidpy/pl/_interactive/__init__.py
squidpy/pl/_interactive/_controller.py
squidpy/pl/_interactive/_model.py
squidpy/pl/_interactive/_utils.py
squidpy/pl/_interactive/_view.py
squidpy/pl/_interactive/_widgets.py
squidpy/pl/_interactive/interactive.py
squidpy/read/__init__.py
squidpy/read/_read.py
squidpy/read/_utils.py
squidpy/tl/__init__.py
squidpy/tl/_sliding_window.py
squidpy/tl/_var_by_distance.py
squidpy-1.7.0.dist-info/METADATA
squidpy-1.7.0.dist-info/WHEEL
squidpy-1.7.0.dist-info/licenses/LICENSE
squidpy-1.7.0.dist-info/RECORD
