Metadata-Version: 2.4
Name: squidpy
Version: 1.7.0
Summary: Spatial Single Cell Analysis in Python
Project-URL: Bug Tracker, https://github.com/scverse/squidpy/issues
Project-URL: Documentation, https://squidpy.readthedocs.io
Project-URL: Home-page, https://github.com/scverse/squidpy
Project-URL: Source, https://github.com/scverse/squidpy
Author: scverse
Maintainer-email: Tim Treis <tim.treis@scverse.org>, Selman Ozleyen <selman.ozleyen@helmholtz-munich.de>
License-Expression: BSD-3-Clause
License-File: LICENSE
Keywords: bio-informatics,image analysis,single-cell,spatial data analysis,spatial transcriptomics
Classifier: Development Status :: 5 - Production/Stable
Classifier: Environment :: Console
Classifier: Framework :: Jupyter
Classifier: Intended Audience :: Science/Research
Classifier: Natural Language :: English
Classifier: Operating System :: MacOS :: MacOS X
Classifier: Operating System :: POSIX :: Linux
Classifier: Programming Language :: Python :: 3 :: Only
Classifier: Programming Language :: Python :: 3.11
Classifier: Programming Language :: Python :: 3.12
Classifier: Programming Language :: Python :: 3.13
Classifier: Programming Language :: Python :: 3.14
Classifier: Topic :: Scientific/Engineering :: Bio-Informatics
Classifier: Topic :: Scientific/Engineering :: Visualization
Classifier: Typing :: Typed
Requires-Python: >=3.11
Requires-Dist: aiohttp>=3.8.1
Requires-Dist: anndata>=0.9
Requires-Dist: cycler>=0.11
Requires-Dist: dask-image>=0.5
Requires-Dist: dask[array]<=2024.11.2,>=2021.2
Requires-Dist: docrep>=0.3.1
Requires-Dist: fsspec>=2021.11
Requires-Dist: imagecodecs<2026,>=2025.8.2
Requires-Dist: matplotlib-scalebar>=0.8
Requires-Dist: matplotlib>=3.3
Requires-Dist: networkx>=2.6
Requires-Dist: numba>=0.56.4
Requires-Dist: numpy>=1.23
Requires-Dist: omnipath>=1.0.7
Requires-Dist: pandas>=2.1
Requires-Dist: pillow>=8
Requires-Dist: scanpy>=1.9.3
Requires-Dist: scikit-image>=0.25
Requires-Dist: scikit-learn>=0.24
Requires-Dist: spatialdata-plot
Requires-Dist: spatialdata>=0.6
Requires-Dist: statsmodels>=0.12
Requires-Dist: tifffile!=2022.4.22
Requires-Dist: tqdm>=4.50.2
Requires-Dist: validators>=0.18.2
Requires-Dist: xarray>=2024.10
Requires-Dist: zarr>=3
Provides-Extra: dev
Requires-Dist: hatch>=1.9; extra == 'dev'
Requires-Dist: ipykernel; extra == 'dev'
Requires-Dist: ipywidgets; extra == 'dev'
Requires-Dist: jupyterlab; extra == 'dev'
Requires-Dist: jupytext; extra == 'dev'
Requires-Dist: notebook; extra == 'dev'
Requires-Dist: pre-commit>=3; extra == 'dev'
Requires-Dist: ruff; extra == 'dev'
Provides-Extra: docs
Requires-Dist: ipython; extra == 'docs'
Requires-Dist: ipywidgets>=8; extra == 'docs'
Requires-Dist: myst-nb>=0.17.1; extra == 'docs'
Requires-Dist: nbsphinx>=0.8.1; extra == 'docs'
Requires-Dist: sphinx-autodoc-annotation; extra == 'docs'
Requires-Dist: sphinx-autodoc-typehints>=1.10.3; extra == 'docs'
Requires-Dist: sphinx-copybutton>=0.5; extra == 'docs'
Requires-Dist: sphinx-design; extra == 'docs'
Requires-Dist: sphinx-rtd-theme; extra == 'docs'
Requires-Dist: sphinx-tabs; extra == 'docs'
Requires-Dist: sphinx>=5.3; extra == 'docs'
Requires-Dist: sphinxcontrib-bibtex>=2.3; extra == 'docs'
Requires-Dist: sphinxcontrib-spelling>=7.6.2; extra == 'docs'
Provides-Extra: test
Requires-Dist: coverage[toml]>=7; extra == 'test'
Requires-Dist: pytest-cov>=4; extra == 'test'
Requires-Dist: pytest-mock>=3.5; extra == 'test'
Requires-Dist: pytest-timeout>=2.1; extra == 'test'
Requires-Dist: pytest-xdist>=3; extra == 'test'
Requires-Dist: pytest>=7; extra == 'test'
Requires-Dist: scanpy[leiden]; extra == 'test'
